LICENSE
MANIFEST.in
README.md
requirements.txt
setup.py
mwdiffs/__init__.py
mwdiffs/mwdiffs.py
mwdiffs.egg-info/PKG-INFO
mwdiffs.egg-info/SOURCES.txt
mwdiffs.egg-info/dependency_links.txt
mwdiffs.egg-info/entry_points.txt
mwdiffs.egg-info/requires.txt
mwdiffs.egg-info/top_level.txt
mwdiffs/utilities/__init__.py
mwdiffs/utilities/dump2diffs.py
mwdiffs/utilities/revdocs2diffs.py
mwdiffs/utilities/util.py
mwdiffs/utilities/tests/__init__.py
mwdiffs/utilities/tests/test_dump2diffs.py