Metadata-Version: 1.1
Name: mwdiffs
Version: 0.0.2
Summary: A set of utilities for processing revision diffs from MediaWiki data.
Home-page: http://pypi.python.org/pypi/mwdiffs
Author: Aaron Halfaker
Author-email: aaron.halfaker@gmail.com
License: The MIT License (MIT)
